phonnx/__init__.py
phonnx/col_preprocessors.py
phonnx/constants.py
phonnx/runtime.py
phonnx/utils/onnx_parsing.py
phonnx/utils/types.py
phonnx-0.1.0.dist-info/LICENSE
phonnx-0.1.0.dist-info/METADATA
phonnx-0.1.0.dist-info/WHEEL
phonnx-0.1.0.dist-info/top_level.txt
phonnx-0.1.0.dist-info/RECORD
