Metadata-Version: 2.1
Name: phonnx
Version: 0.1.0
Summary: Python Hypercharged ONNX Runtime.
Author-email: Oleh Kostromin <kostromin97@gmail.com>, Iryna Kondrashchenko <iryna230520@gmail.com>
License: MIT
Classifier: Programming Language :: Python :: 3
Classifier: License :: OSI Approved :: MIT License
Classifier: Operating System :: OS Independent
Requires-Python: >=3.9
License-File: LICENSE
Requires-Dist: numpy >=1.18.0
Requires-Dist: onnx >=1.12.0
Requires-Dist: onnxruntime >=1.12.1
